{
  "falcons": {
    "team": "Atlanta Falcons",
    "wins": "3",
    "losses": "7",
    "record_text": "3–7",
    "division_standing": "3rd",
    "conf_standing": "13",
    "season_status": "Regular Season",
    "wins_away": 3.5,
    "ppg": "19.5",
    "opp_ppg": "23.9",
    "ppg_rank": "#27",
    "opp_ppg_rank": "#19",
    "rpg": "119.9",
    "opp_rpg": "138.5",
    "rpg_rank": "#13",
    "opp_rpg_rank": "#28",
    "papg": "212.6",
    "opp_papg": "188.0",
    "papg_rank": "#18",
    "opp_papg_rank": "#6"
  },
  "hawks": {
    "team": "Atlanta Hawks",
    "wins": "9",
    "losses": "6",
    "record_text": "9–6 (.600)",
    "standings_text": "Division: 1st (Southeast)Conference: 3rd (Eastern)",
    "conf_standings": "3rd",
    "division_standings": "1st",
    "season_status": "Regular Season",
    "ppg": "117.2",
    "opp_ppg": "114.4",
    "ppg_rank": "#18",
    "opp_ppg_rank": "#11",
    "sppg": "48.6%",
    "opp_sppg": "45.9%",
    "sppg_rank": "#8",
    "opp_sppg_rank": "#10"
  },
  "braves": {
    "team": "Atlanta Braves",
    "wins": 76,
    "losses": 86,
    "record_text": "76–86",
    "standings_text": "4th",
    "season_ongoing": "NO"
  },
  "gt": {
    "team": "Georgia Tech Yellow Jackets",
    "wins": 9,
    "losses": 1,
    "record_text": "9–1",
    "ranking": "No. 16",
    "conf_record": "6–1",
    "conf_standings": 1,
    "season_status": "Regular Season",
    "ppg": "33.4",
    "opp_ppg": "25.6",
    "ppg_rank": "#21",
    "opp_ppg_rank": "#68",
    "rpg": "224.8",
    "opp_rpg": "171.4",
    "rpg_rank": "#9",
    "opp_rpg_rank": "#96",
    "papg": "251.6",
    "opp_papg": "247.0",
    "papg_rank": "#39",
    "opp_papg_rank": "#98"
  }
}